<?xml version="1.0"?>
<!DOCTYPE hibernate-mapping PUBLIC "-//Hibernate/Hibernate Mapping DTD 3.0//EN"
"http://hibernate.sourceforge.net/hibernate-mapping-3.0.dtd">
<!-- Generated 2016-5-17 16:08:46 by Hibernate Tools 3.5.0.Final -->
<hibernate-mapping>
    <class name="com.june.Entity.Employee" table="EMPLOYEE">
        <id name="employeeId" type="int">
            <column name="EMPLOYEEID" />
            <generator class="assigned" />
        </id>
        <property name="employeeName" type="java.lang.String">
            <column name="EMPLOYEENAME" />
        </property>
        <property name="deptId" type="int">
            <column name="DEPTID" />
        </property>
    </class>
</hibernate-mapping>
